asq/__init__.py
asq/_types.py
asq/comparers.py
asq/extension.py
asq/initiators.py
asq/namedelements.py
asq/parallel_queryable.py
asq/predicates.py
asq/queryables.py
asq/record.py
asq/selectors.py
asq/version.py
asq-2.0.0.dist-info/LICENCE.txt
asq-2.0.0.dist-info/METADATA
asq-2.0.0.dist-info/WHEEL
asq-2.0.0.dist-info/top_level.txt
asq-2.0.0.dist-info/zip-safe
asq-2.0.0.dist-info/RECORD
