Metadata-Version: 2.1
Name: asq
Version: 2.0.0
Summary: LINQ-for-objects style queries for Python iterables.
Home-page: https://github.com/sixty-north/asq
Author: Sixty North AS
Author-email: systems+asq@sixty-north.com
License: MIT License
Keywords: iterators iterables Python LINQ
Classifier: Development Status :: 5 - Production/Stable
Classifier: Intended Audience :: Developers
Classifier: Topic :: Software Development :: Libraries :: Python Modules
Classifier: License :: OSI Approved :: MIT License
Classifier: Programming Language :: Python :: 3 :: Only
Classifier: Programming Language :: Python :: 3.9
Classifier: Programming Language :: Python :: 3.10
Classifier: Programming Language :: Python :: 3.11
Classifier: Programming Language :: Python :: 3.12
License-File: LICENCE.txt
Provides-Extra: dev
Requires-Dist: bumpversion ; extra == 'dev'
Provides-Extra: doc
Requires-Dist: sphinx ; extra == 'doc'
Requires-Dist: sphinx-rtd-theme ; extra == 'doc'
Requires-Dist: better-apidoc ; extra == 'doc'
Provides-Extra: test
Requires-Dist: pytest ; extra == 'test'
Requires-Dist: coverage ; extra == 'test'
Requires-Dist: pytest-cov ; extra == 'test'
Requires-Dist: hypothesis ; extra == 'test'
Requires-Dist: tox ; extra == 'test'
